Workbook

Sheet Hypotheses
A1: TotalEnergies – Hypothèses du modèle DCF
A2: Légende : bleu = saisie · noir = formule · vert = lien inter-feuilles · fond jaune = hypothèse clé à challenger. Montants en M$ sauf mention.
A4: Paramètres généraux | B4: Valeur | C4: Unité | D4: Source / commentaire
A5: Scénario retenu (1=Bas, 2=Central, 3=Haut) | B5: 2 | C5: =CHOOSE(B5,"Bas","Central","Haut") -> Central | D5: Sélecteur : pilote les lignes « Retenu » ci-dessous
A6: WACC | B6: 0.09 | C6: % | D6: Hypothèse illustrative – à construire (CAPM, bêta, structure cible)
A7: Croissance terminale (g) | B7: 0.01 | C7: % | D7: Hypothèse illustrative – déclin pétrolier long terme vs transition
A8: Taux d'impôt sur charges financières | B8: 0.35 | C8: % | D8: Hypothèse illustrative
A9: Taux de change (EUR pour 1 USD) | B9: 0.86 | C9: EUR/USD | D9: À METTRE À JOUR avec le spot du jour
A10: Cours actuel de l'action (EUR) | C10: EUR | D10: À SAISIR (Euronext Paris : TTE) pour calculer le potentiel
A12: Bilan et capital (FY2025) | B12: Valeur | C12: Unité | D12: Source / commentaire
A13: Capitaux propres | B13: 117523 | C13: M$ | D13: Form 20-F FY2025 (SEC) – vérifier l'inclusion des minoritaires
A14: Gearing | B14: 0.15 | C14: % | D14: Communiqué résultats FY2025 : gearing ≈ 15 %
A15: Dette nette (estimée via le gearing) | B15: =B13*B14/(1-B14) -> 20739.353 | C15: M$ | D15: Estimation : à remplacer par la dette nette publiée
A16: Actions diluées (moyenne pondérée) | B16: 2214 | C16: M | D16: Communiqué résultats FY2025
A17: Trésorerie et équivalents (info) | B17: 26202 | C17: M$ | D17: Form 20-F FY2025
A18: Dette financière non courante (info) | B18: 48995 | C18: M$ | D18: Form 20-F FY2025
A21: Scénarios opérationnels | B21: 2026E | C21: 2027E | D21: 2028E | E21: 2029E | F21: 2030E
A22: Croissance des ventes
A23: Bas | B23: -0.05 | C23: -0.02 | D23: 0 | E23: 0.01 | F23: 0.01
A24: Central | B24: 0 | C24: 0.02 | D24: 0.02 | E24: 0.02 | F24: 0.02
A25: Haut | B25: 0.03 | C25: 0.03 | D25: 0.03 | E25: 0.025 | F25: 0.025
A26: Retenu | B26: =CHOOSE($B$5,B23,B24,B25) -> 0 | C26: =CHOOSE($B$5,C23,C24,C25) -> 0.02 | D26: =CHOOSE($B$5,D23,D24,D25) -> 0.02 | E26: =CHOOSE($B$5,E23,E24,E25) -> 0.02 | F26: =CHOOSE($B$5,F23,F24,F25) -> 0.02
A27: Marge CFFO / ventes
A28: Bas | B28: 0.12 | C28: 0.12 | D28: 0.12 | E28: 0.12 | F28: 0.12
A29: Central | B29: 0.138 | C29: 0.138 | D29: 0.138 | E29: 0.138 | F29: 0.138
A30: Haut | B30: 0.15 | C30: 0.15 | D30: 0.15 | E30: 0.15 | F30: 0.15
A31: Retenu | B31: =CHOOSE($B$5,B28,B29,B30) -> 0.138 | C31: =CHOOSE($B$5,C28,C29,C30) -> 0.138 | D31: =CHOOSE($B$5,D28,D29,D30) -> 0.138 | E31: =CHOOSE($B$5,E28,E29,E30) -> 0.138 | F31: =CHOOSE($B$5,F28,F29,F30) -> 0.138
A32: Investissements nets (M$)
A33: Bas | B33: 15000 | C33: 15000 | D33: 15000 | E33: 15000 | F33: 15000
A34: Central | B34: 15000 | C34: 15000 | D34: 15000 | E34: 15000 | F34: 15000
A35: Haut | B35: 16000 | C35: 16000 | D35: 16000 | E35: 16000 | F35: 16000
A36: Retenu | B36: =CHOOSE($B$5,B33,B34,B35) -> 15000 | C36: =CHOOSE($B$5,C33,C34,C35) -> 15000 | D36: =CHOOSE($B$5,D33,D34,D35) -> 15000 | E36: =CHOOSE($B$5,E33,E34,E35) -> 15000 | F36: =CHOOSE($B$5,F33,F34,F35) -> 15000
A37: Hypothèses opérationnelles purement illustratives (pas de prévision officielle). Marge CFFO centrale ≈ marge 2025 (27,8 Md$ / 201,2 Md$). Investissements nets centraux ≈ 15 Md$/an (ordre de grandeur de la guidance, à vérifier).

Sheet Historique
A1: TotalEnergies – Données historiques
A4: (M$ sauf mention) | B4: 2024 | C4: 2025 | D4: Source
A5: Ventes (Sales) | B5: 214550 | C5: 201196 | D5: Comptes consolidés Q4 2025
A6: Revenus des ventes | B6: 195610 | C6: 182344 | D6: Comptes consolidés Q4 2025
A7: Résultat net IFRS (part du Groupe) | B7: 15758 | C7: 13127 | D7: Comptes consolidés Q4 2025
A8: Résultat net ajusté (part du Groupe) | B8: n.d. | C8: 15587 | D8: Communiqué FY2025
A9: CFFO (hors variation de BFR) | B9: n.d. | C9: 27800 | D9: Communiqué FY2025 : 27,8 Md$ (arrondi)
A10: Flux de trésorerie d'exploitation (IFRS) | B10: 30854 | C10: 27343 | D10: Form 20-F FY2025
A11: Investissements nets | B11: n.d. | C11: 17091 | D11: Communiqué FY2025
A12: Coût de l'endettement net | B12: 1230 | C12: 2067 | D12: Comptes consolidés Q4 2025
A13: Actions diluées moyennes (M) | B13: n.d. | C13: 2214 | D13: Communiqué FY2025
A14: ROACE | B14: n.d. | C14: 0.126 | D14: Communiqué FY2025
A15: Dividende par action (EUR) | B15: n.d. | C15: 3.4 | D15: Communiqué FY2025 (AG du 29/05/2026)
A17: Ratios
A18: Croissance des ventes | C18: =C5/B5-1 -> -0.062241902
A19: Marge CFFO / ventes | C19: =C9/C5 -> 0.13817372
A20: Marge nette ajustée / ventes | C20: =C8/C5 -> 0.077471719
A21: Investissements nets / CFFO | C21: =C11/C9 -> 0.61478417

Sheet DCF
A1: TotalEnergies – DCF (flux disponibles pour la firme)
A2: ="Scénario : "&Hypotheses!C5&" · valorisation au 31/12/2025 · actualisation fin de période" -> Scénario : Central · valorisation au 31/12/2025 · actualisation fin de période
A4: (M$) | B4: 2025A | C4: 2026E | D4: 2027E | E4: 2028E | F4: 2029E | G4: 2030E
A5: Période d'actualisation (t) | B5: 0 | C5: 1 | D5: 2 | E5: 3 | F5: 4 | G5: 5
A6: Ventes | B6: =Historique!C5 -> 201196 | C6: =B6*(1+Hypotheses!B26) -> 201196 | D6: =C6*(1+Hypotheses!C26) -> 205219.92 | E6: =D6*(1+Hypotheses!D26) -> 209324.32 | F6: =E6*(1+Hypotheses!E26) -> 213510.8 | G6: =F6*(1+Hypotheses!F26) -> 217781.02
A7: Croissance | C7: =C6/B6-1 -> 0 | D7: =D6/C6-1 -> 0.02 | E7: =E6/D6-1 -> 0.02 | F7: =F6/E6-1 -> 0.02 | G7: =G6/F6-1 -> 0.02
A8: Marge CFFO / ventes | B8: =B9/B6 -> 0.13817372 | C8: =Hypotheses!B31 -> 0.138 | D8: =Hypotheses!C31 -> 0.138 | E8: =Hypotheses!D31 -> 0.138 | F8: =Hypotheses!E31 -> 0.138 | G8: =Hypotheses!F31 -> 0.138
A9: CFFO (hors BFR) | B9: =Historique!C9 -> 27800 | C9: =C6*C8 -> 27765.048 | D9: =D6*D8 -> 28320.349 | E9: =E6*E8 -> 28886.756 | F9: =F6*F8 -> 29464.491 | G9: =G6*G8 -> 30053.781
A10: + Charges financières nettes après impôt | B10: =Historique!C12*(1-Hypotheses!B8) -> 1343.55 | C10: =B10 -> 1343.55 | D10: =C10 -> 1343.55 | E10: =D10 -> 1343.55 | F10: =E10 -> 1343.55 | G10: =F10 -> 1343.55
A11: – Investissements nets | B11: =Historique!C11 -> 17091 | C11: =Hypotheses!B36 -> 15000 | D11: =Hypotheses!C36 -> 15000 | E11: =Hypotheses!D36 -> 15000 | F11: =Hypotheses!E36 -> 15000 | G11: =Hypotheses!F36 -> 15000
A12: Flux disponible pour la firme (FCFF) | B12: =B9+B10-B11 -> 12052.55 | C12: =C9+C10-C11 -> 14108.598 | D12: =D9+D10-D11 -> 14663.899 | E12: =E9+E10-E11 -> 15230.306 | F12: =F9+F10-F11 -> 15808.041 | G12: =G9+G10-G11 -> 16397.331
A13: Facteur d'actualisation | C13: =1/(1+Hypotheses!$B$6)^C5 -> 0.91743119 | D13: =1/(1+Hypotheses!$B$6)^D5 -> 0.84167999 | E13: =1/(1+Hypotheses!$B$6)^E5 -> 0.77218348 | F13: =1/(1+Hypotheses!$B$6)^F5 -> 0.70842521 | G13: =1/(1+Hypotheses!$B$6)^G5 -> 0.64993139
A14: FCFF actualisé | C14: =C12*C13 -> 12943.668 | D14: =D12*D13 -> 12342.31 | E14: =E12*E13 -> 11760.591 | F14: =F12*F13 -> 11198.815 | G14: =G12*G13 -> 10657.14
A16: Valorisation
A17: Somme des FCFF actualisés | B17: =SUM(C14:G14) -> 58902.524
A18: FCFF terminal (2031) | B18: =G12*(1+Hypotheses!B7) -> 16561.304
A19: Valeur terminale | B19: =IF(Hypotheses!B6>Hypotheses!B7,B18/(Hypotheses!B6-Hypotheses!B7),NA()) -> 207016.3
A20: Valeur terminale actualisée | B20: =B19*G13 -> 134546.39
A21: Valeur d'entreprise (VE) | B21: =B17+B20 -> 193448.92
A22: – Dette nette | B22: =Hypotheses!B15 -> 20739.353
A23: Valeur des capitaux propres | B23: =B21-B22 -> 172709.56
A24: Actions diluées (M) | B24: =Hypotheses!B16 -> 2214
A25: Valeur par action (USD) | B25: =B23/B24 -> 78.007933
A26: Valeur par action (EUR) | B26: =B25*Hypotheses!B9 -> 67.086822
A27: Cours actuel (EUR) | B27: =IF(ISNUMBER(Hypotheses!B10),Hypotheses!B10,"n.d.") -> n.d.
A28: Potentiel / (décote) vs cours | B28: =IF(ISNUMBER(B27),B26/B27-1,"n.d.") -> n.d.
A29: Poids de la VT dans la VE | B29: =B20/B21 -> 0.69551381
A30: VE implicite / CFFO 2025 | B30: =B21/B9 -> 6.9585941
A32: Limites : FCFF approché (CFFO + frais financiers après impôt – investissements nets) ; pas de bridge EBITDA/NOPAT, pas de minoritaires ni de provisions de fin de vie. À affiner par segment (E&P, LNG, Power, Downstream).

Sheet Sensibilite
A1: Sensibilité – valeur par action (EUR) : WACC × croissance terminale
A4: WACC \ g | B4: 0 | C4: 0.005 | D4: 0.01 | E4: 0.015 | F4: 0.02
A5: 0.07 | B5: =(SUMPRODUCT(DCF!$C$12:$G$12/(1+$A5)^DCF!$C$5:$G$5)+DCF!$G$12*(1+B$4)/($A5-B$4)/(1+$A5)^DCF!$G$5-Hypotheses!$B$15)/Hypotheses!$B$16*Hypotheses!$B$9 -> 80.970894 | C5: =(SUMPRODUCT(DCF!$C$12:$G$12/(1+$A5)^DCF!$C$5:$G$5)+DCF!$G$12*(1+C$4)/($A5-C$4)/(1+$A5)^DCF!$G$5-Hypotheses!$B$15)/Hypotheses!$B$16*Hypotheses!$B$9 -> 86.310602 | D5: =(SUMPRODUCT(DCF!$C$12:$G$12/(1+$A5)^DCF!$C$5:$G$5)+DCF!$G$12*(1+D$4)/($A5-D$4)/(1+$A5)^DCF!$G$5-Hypotheses!$B$15)/Hypotheses!$B$16*Hypotheses!$B$9 -> 92.540261 | E5: =(SUMPRODUCT(DCF!$C$12:$G$12/(1+$A5)^DCF!$C$5:$G$5)+DCF!$G$12*(1+E$4)/($A5-E$4)/(1+$A5)^DCF!$G$5-Hypotheses!$B$15)/Hypotheses!$B$16*Hypotheses!$B$9 -> 99.902585 | F5: =(SUMPRODUCT(DCF!$C$12:$G$12/(1+$A5)^DCF!$C$5:$G$5)+DCF!$G$12*(1+F$4)/($A5-F$4)/(1+$A5)^DCF!$G$5-Hypotheses!$B$15)/Hypotheses!$B$16*Hypotheses!$B$9 -> 108.73737
A6: 0.08 | B6: =(SUMPRODUCT(DCF!$C$12:$G$12/(1+$A6)^DCF!$C$5:$G$5)+DCF!$G$12*(1+B$4)/($A6-B$4)/(1+$A6)^DCF!$G$5-Hypotheses!$B$15)/Hypotheses!$B$16*Hypotheses!$B$9 -> 69.63218 | C6: =(SUMPRODUCT(DCF!$C$12:$G$12/(1+$A6)^DCF!$C$5:$G$5)+DCF!$G$12*(1+C$4)/($A6-C$4)/(1+$A6)^DCF!$G$5-Hypotheses!$B$15)/Hypotheses!$B$16*Hypotheses!$B$9 -> 73.533555 | D6: =(SUMPRODUCT(DCF!$C$12:$G$12/(1+$A6)^DCF!$C$5:$G$5)+DCF!$G$12*(1+D$4)/($A6-D$4)/(1+$A6)^DCF!$G$5-Hypotheses!$B$15)/Hypotheses!$B$16*Hypotheses!$B$9 -> 77.99227 | E6: =(SUMPRODUCT(DCF!$C$12:$G$12/(1+$A6)^DCF!$C$5:$G$5)+DCF!$G$12*(1+E$4)/($A6-E$4)/(1+$A6)^DCF!$G$5-Hypotheses!$B$15)/Hypotheses!$B$16*Hypotheses!$B$9 -> 83.136941 | F6: =(SUMPRODUCT(DCF!$C$12:$G$12/(1+$A6)^DCF!$C$5:$G$5)+DCF!$G$12*(1+F$4)/($A6-F$4)/(1+$A6)^DCF!$G$5-Hypotheses!$B$15)/Hypotheses!$B$16*Hypotheses!$B$9 -> 89.139056
A7: 0.09 | B7: =(SUMPRODUCT(DCF!$C$12:$G$12/(1+$A7)^DCF!$C$5:$G$5)+DCF!$G$12*(1+B$4)/($A7-B$4)/(1+$A7)^DCF!$G$5-Hypotheses!$B$15)/Hypotheses!$B$16*Hypotheses!$B$9 -> 60.819883 | C7: =(SUMPRODUCT(DCF!$C$12:$G$12/(1+$A7)^DCF!$C$5:$G$5)+DCF!$G$12*(1+C$4)/($A7-C$4)/(1+$A7)^DCF!$G$5-Hypotheses!$B$15)/Hypotheses!$B$16*Hypotheses!$B$9 -> 63.769031 | D7: =(SUMPRODUCT(DCF!$C$12:$G$12/(1+$A7)^DCF!$C$5:$G$5)+DCF!$G$12*(1+D$4)/($A7-D$4)/(1+$A7)^DCF!$G$5-Hypotheses!$B$15)/Hypotheses!$B$16*Hypotheses!$B$9 -> 67.086822 | E7: =(SUMPRODUCT(DCF!$C$12:$G$12/(1+$A7)^DCF!$C$5:$G$5)+DCF!$G$12*(1+E$4)/($A7-E$4)/(1+$A7)^DCF!$G$5-Hypotheses!$B$15)/Hypotheses!$B$16*Hypotheses!$B$9 -> 70.846986 | F7: =(SUMPRODUCT(DCF!$C$12:$G$12/(1+$A7)^DCF!$C$5:$G$5)+DCF!$G$12*(1+F$4)/($A7-F$4)/(1+$A7)^DCF!$G$5-Hypotheses!$B$15)/Hypotheses!$B$16*Hypotheses!$B$9 -> 75.144316
A8: 0.1 | B8: =(SUMPRODUCT(DCF!$C$12:$G$12/(1+$A8)^DCF!$C$5:$G$5)+DCF!$G$12*(1+B$4)/($A8-B$4)/(1+$A8)^DCF!$G$5-Hypotheses!$B$15)/Hypotheses!$B$16*Hypotheses!$B$9 -> 53.775794 | C8: =(SUMPRODUCT(DCF!$C$12:$G$12/(1+$A8)^DCF!$C$5:$G$5)+DCF!$G$12*(1+C$4)/($A8-C$4)/(1+$A8)^DCF!$G$5-Hypotheses!$B$15)/Hypotheses!$B$16*Hypotheses!$B$9 -> 56.065447 | D8: =(SUMPRODUCT(DCF!$C$12:$G$12/(1+$A8)^DCF!$C$5:$G$5)+DCF!$G$12*(1+D$4)/($A8-D$4)/(1+$A8)^DCF!$G$5-Hypotheses!$B$15)/Hypotheses!$B$16*Hypotheses!$B$9 -> 58.609506 | E8: =(SUMPRODUCT(DCF!$C$12:$G$12/(1+$A8)^DCF!$C$5:$G$5)+DCF!$G$12*(1+E$4)/($A8-E$4)/(1+$A8)^DCF!$G$5-Hypotheses!$B$15)/Hypotheses!$B$16*Hypotheses!$B$9 -> 61.452866 | F8: =(SUMPRODUCT(DCF!$C$12:$G$12/(1+$A8)^DCF!$C$5:$G$5)+DCF!$G$12*(1+F$4)/($A8-F$4)/(1+$A8)^DCF!$G$5-Hypotheses!$B$15)/Hypotheses!$B$16*Hypotheses!$B$9 -> 64.651646
A9: 0.11 | B9: =(SUMPRODUCT(DCF!$C$12:$G$12/(1+$A9)^DCF!$C$5:$G$5)+DCF!$G$12*(1+B$4)/($A9-B$4)/(1+$A9)^DCF!$G$5-Hypotheses!$B$15)/Hypotheses!$B$16*Hypotheses!$B$9 -> 48.017434 | C9: =(SUMPRODUCT(DCF!$C$12:$G$12/(1+$A9)^DCF!$C$5:$G$5)+DCF!$G$12*(1+C$4)/($A9-C$4)/(1+$A9)^DCF!$G$5-Hypotheses!$B$15)/Hypotheses!$B$16*Hypotheses!$B$9 -> 49.833745 | D9: =(SUMPRODUCT(DCF!$C$12:$G$12/(1+$A9)^DCF!$C$5:$G$5)+DCF!$G$12*(1+D$4)/($A9-D$4)/(1+$A9)^DCF!$G$5-Hypotheses!$B$15)/Hypotheses!$B$16*Hypotheses!$B$9 -> 51.831686 | E9: =(SUMPRODUCT(DCF!$C$12:$G$12/(1+$A9)^DCF!$C$5:$G$5)+DCF!$G$12*(1+E$4)/($A9-E$4)/(1+$A9)^DCF!$G$5-Hypotheses!$B$15)/Hypotheses!$B$16*Hypotheses!$B$9 -> 54.039937 | F9: =(SUMPRODUCT(DCF!$C$12:$G$12/(1+$A9)^DCF!$C$5:$G$5)+DCF!$G$12*(1+F$4)/($A9-F$4)/(1+$A9)^DCF!$G$5-Hypotheses!$B$15)/Hypotheses!$B$16*Hypotheses!$B$9 -> 56.49355
A11: Contrôle vs DCF (0 si WACC/g du modèle sont dans la grille) | B11: =IFERROR(ROUND(INDEX(B5:F9,MATCH(Hypotheses!B6,A5:A9,0),MATCH(Hypotheses!B7,B4:F4,0))-DCF!B26,6),"hors grille") -> 0
